jaxcapse/__init__.py
jaxcapse/data_fetcher.py
jaxcapse/jaxcapse.py
jaxcapse-0.1.2.dist-info/LICENSE
jaxcapse-0.1.2.dist-info/METADATA
jaxcapse-0.1.2.dist-info/WHEEL
jaxcapse-0.1.2.dist-info/RECORD
