Metadata-Version: 2.1
Name: jaxcapse
Version: 0.1.2
Summary: JAX implementation of the Capse emulator.
Author: marcobonici
Author-email: bonici.marco@gmail.com
Requires-Python: >=3.10,<4.0
Classifier: Programming Language :: Python :: 3
Classifier: Programming Language :: Python :: 3.10
Classifier: Programming Language :: Python :: 3.11
Classifier: Programming Language :: Python :: 3.12
Requires-Dist: flax (>=0.10.0,<0.11.0)
Requires-Dist: jax (>=0.4.30,<0.5.0)
Requires-Dist: jaxace (>=0.1.1,<0.2.0)
